pretok/__init__.py
pretok/_version.py
pretok/py.typed
pretok/capability/__init__.py
pretok/capability/registry.py
pretok/config/__init__.py
pretok/config/loader.py
pretok/config/schema.py
pretok/detection/__init__.py
pretok/detection/base.py
pretok/detection/composite.py
pretok/detection/fasttext_backend.py
pretok/detection/langdetect_backend.py
pretok/pipeline/__init__.py
pretok/pipeline/cache.py
pretok/pipeline/core.py
pretok/segment/__init__.py
pretok/segment/lexer.py
pretok/segment/types.py
pretok/translation/__init__.py
pretok/translation/base.py
pretok/translation/factory.py
pretok/translation/huggingface.py
pretok/translation/llm.py
pretok-0.1.2.dist-info/METADATA
pretok-0.1.2.dist-info/WHEEL
pretok-0.1.2.dist-info/licenses/LICENSE
pretok-0.1.2.dist-info/RECORD
