Metadata-Version: 2.4
Name: pretok
Version: 0.1.2
Summary: Universal pre-token language adaptation layer for text-based LLMs
Project-URL: Homepage, https://github.com/yen0304/pretok
Project-URL: Documentation, https://github.com/yen0304/pretok#readme
Project-URL: Repository, https://github.com/yen0304/pretok
Project-URL: Issues, https://github.com/yen0304/pretok/issues
Author-email: yen0304 <asce55123@gmail.com>
License: MIT
License-File: LICENSE
Keywords: language-detection,llm,nlp,pre-tokenization,translation
Classifier: Development Status :: 3 - Alpha
Classifier: Intended Audience :: Developers
Classifier: License :: OSI Approved :: MIT License
Classifier: Programming Language :: Python :: 3
Classifier: Programming Language :: Python :: 3.11
Classifier: Programming Language :: Python :: 3.12
Classifier: Programming Language :: Python :: 3.13
Classifier: Topic :: Scientific/Engineering :: Artificial Intelligence
Classifier: Topic :: Text Processing :: Linguistic
Classifier: Typing :: Typed
Requires-Python: >=3.11
Requires-Dist: pydantic>=2.0
Requires-Dist: pyyaml>=6.0
Provides-Extra: all
Requires-Dist: deepl>=1.0; extra == 'all'
Requires-Dist: fasttext-wheel>=0.9.2; extra == 'all'
Requires-Dist: google-cloud-translate>=3.0; extra == 'all'
Requires-Dist: langdetect>=1.0.9; extra == 'all'
Requires-Dist: openai>=1.0; extra == 'all'
Requires-Dist: redis>=4.0; extra == 'all'
Requires-Dist: sentencepiece>=0.1.99; extra == 'all'
Requires-Dist: torch>=2.0; extra == 'all'
Requires-Dist: transformers>=4.30; extra == 'all'
Provides-Extra: api
Requires-Dist: deepl>=1.0; extra == 'api'
Requires-Dist: google-cloud-translate>=3.0; extra == 'api'
Requires-Dist: openai>=1.0; extra == 'api'
Provides-Extra: deepl
Requires-Dist: deepl>=1.0; extra == 'deepl'
Provides-Extra: detection
Requires-Dist: fasttext-wheel>=0.9.2; extra == 'detection'
Requires-Dist: langdetect>=1.0.9; extra == 'detection'
Provides-Extra: dev
Requires-Dist: hypothesis>=6.0; extra == 'dev'
Requires-Dist: mypy>=1.8; extra == 'dev'
Requires-Dist: pre-commit>=3.0; extra == 'dev'
Requires-Dist: pytest-asyncio>=0.23; extra == 'dev'
Requires-Dist: pytest-cov>=4.0; extra == 'dev'
Requires-Dist: pytest>=8.0; extra == 'dev'
Requires-Dist: ruff>=0.4; extra == 'dev'
Provides-Extra: docs
Requires-Dist: mkdocs-material>=9.0; extra == 'docs'
Requires-Dist: mkdocs>=1.5; extra == 'docs'
Requires-Dist: mkdocstrings[python]>=0.24; extra == 'docs'
Provides-Extra: fasttext
Requires-Dist: fasttext-wheel>=0.9.2; extra == 'fasttext'
Provides-Extra: google
Requires-Dist: google-cloud-translate>=3.0; extra == 'google'
Provides-Extra: langdetect
Requires-Dist: langdetect>=1.0.9; extra == 'langdetect'
Provides-Extra: local
Requires-Dist: sentencepiece>=0.1.99; extra == 'local'
Requires-Dist: torch>=2.0; extra == 'local'
Requires-Dist: transformers>=4.30; extra == 'local'
Provides-Extra: m2m100
Requires-Dist: sentencepiece>=0.1.99; extra == 'm2m100'
Requires-Dist: torch>=2.0; extra == 'm2m100'
Requires-Dist: transformers>=4.30; extra == 'm2m100'
Provides-Extra: nllb
Requires-Dist: sentencepiece>=0.1.99; extra == 'nllb'
Requires-Dist: torch>=2.0; extra == 'nllb'
Requires-Dist: transformers>=4.30; extra == 'nllb'
Provides-Extra: openai
Requires-Dist: openai>=1.0; extra == 'openai'
Provides-Extra: redis
Requires-Dist: redis>=4.0; extra == 'redis'
